knoema/__init__.py
knoema/api_client.py
knoema/api_config.py
knoema/api_definitions.py
knoema/api_definitions_search.py
knoema/api_definitions_sema.py
knoema/data_reader.py
knoema/upload_frame.py
knoema/view_definitions.py
knoema-1.3.1.dist-info/LICENSE
knoema-1.3.1.dist-info/METADATA
knoema-1.3.1.dist-info/WHEEL
knoema-1.3.1.dist-info/top_level.txt
knoema-1.3.1.dist-info/RECORD
