Metadata-Version: 2.2
Name: knoema
Version: 1.3.1
Summary: Official Python package for Knoema's API
Home-page: https://github.com/Knoema/knoema-python-driver
Author: Knoema
Author-email: Knoema <info@knoema.com>
License: MIT License
Project-URL: Homepage, https://github.com/Knoema/knoema-python-driver
Project-URL: Repository, https://github.com/Knoema/knoema-python-driver.git
Project-URL: Issues, https://github.com/Knoema/knoema-python-driver/issues
Keywords: API,knoema
Classifier: Programming Language :: Python :: 3 :: Only
Classifier: License :: OSI Approved :: MIT License
Classifier: Development Status :: 5 - Production/Stable
Classifier: Operating System :: OS Independent
Requires-Python: >=3.9
License-File: LICENSE
Requires-Dist: pandas>=2.0.0
Requires-Dist: pytest-shutil==1.7.0
Dynamic: author
Dynamic: home-page
